jodel_ios_api/__init__.py
jodel_ios_api/jodel_ios_api.py
jodel_ios_api-1.0.2.dist-info/LICENSE.txt
jodel_ios_api-1.0.2.dist-info/METADATA
jodel_ios_api-1.0.2.dist-info/WHEEL
jodel_ios_api-1.0.2.dist-info/top_level.txt
jodel_ios_api-1.0.2.dist-info/RECORD
