Metadata-Version: 2.1
Name: jodel-ios-api
Version: 1.0.2
Summary: Unoffical Python Interface to the Jodel API (based on iOS)
Home-page: https://github.com/marbink/jodel_ios_api
Author: marbink
Author-email: github@marbink.eu
License: MIT
Keywords: jodel
Platform: UNKNOWN
Classifier: Development Status :: 5 - Production/Stable
Classifier: License :: OSI Approved :: MIT License
Classifier: Intended Audience :: Developers
Classifier: Programming Language :: Python :: 2
Classifier: Programming Language :: Python :: 2.7
Classifier: Programming Language :: Python :: 3
Classifier: Programming Language :: Python :: 3.6
Classifier: Topic :: Internet :: WWW/HTTP
Classifier: Topic :: Internet :: WWW/HTTP :: Dynamic Content :: Message Boards
Classifier: Topic :: Software Development :: Libraries :: Python Modules
Requires-Dist: requests
Requires-Dist: future
Requires-Dist: simplejson
